[{"date": "2023-10-25", "open": 119.795, "close": 119.935, "high": 119.945, "low": 119.746, "volume": 25837}, {"date": "2023-10-26", "open": 119.964, "close": 119.967, "high": 120.024, "low": 119.946, "volume": 17155}, {"date": "2023-10-27", "open": 119.967, "close": 119.977, "high": 120.026, "low": 119.936, "volume": 20552}, {"date": "2023-10-30", "open": 119.978, "close": 120.026, "high": 120.053, "low": 119.958, "volume": 24353}, {"date": "2023-10-31", "open": 120.037, "close": 120.186, "high": 120.256, "low": 120.037, "volume": 21035}, {"date": "2023-11-01", "open": 120.196, "close": 120.312, "high": 120.316, "low": 120.196, "volume": 30003}, {"date": "2023-11-02", "open": 120.317, "close": 120.433, "high": 120.44, "low": 120.317, "volume": 25452}, {"date": "2023-11-03", "open": 120.436, "close": 120.421, "high": 120.53, "low": 120.339, "volume": 24195}, {"date": "2023-11-06", "open": 120.424, "close": 120.408, "high": 120.445, "low": 120.298, "volume": 25895}, {"date": "2023-11-07", "open": 120.435, "close": 120.472, "high": 120.554, "low": 120.411, "volume": 20609}, {"date": "2023-11-08", "open": 120.455, "close": 120.48, "high": 120.492, "low": 120.365, "volume": 25132}, {"date": "2023-11-09", "open": 120.475, "close": 120.487, "high": 120.516, "low": 120.443, "volume": 22001}, {"date": "2023-11-10", "open": 120.488, "close": 120.504, "high": 120.538, "low": 120.467, "volume": 23828}, {"date": "2023-11-13", "open": 120.501, "close": 120.559, "high": 120.562, "low": 120.475, "volume": 19163}, {"date": "2023-11-14", "open": 120.521, "close": 120.488, "high": 120.607, "low": 120.465, "volume": 20097}, {"date": "2023-11-15", "open": 120.459, "close": 120.452, "high": 120.535, "low": 120.436, "volume": 19838}, {"date": "2023-11-16", "open": 120.453, "close": 120.55, "high": 120.591, "low": 120.453, "volume": 20823}, {"date": "2023-11-17", "open": 120.586, "close": 120.6, "high": 120.619, "low": 120.536, "volume": 23355}, {"date": "2023-11-20", "open": 120.6, "close": 120.597, "high": 120.614, "low": 120.565, "volume": 18564}, {"date": "2023-11-21", "open": 120.597, "close": 120.624, "high": 120.639, "low": 120.539, "volume": 23524}, {"date": "2023-11-22", "open": 120.624, "close": 120.557, "high": 120.624, "low": 120.555, "volume": 21617}, {"date": "2023-11-23", "open": 120.539, "close": 120.39, "high": 120.539, "low": 120.386, "volume": 23643}, {"date": "2023-11-24", "open": 120.398, "close": 120.408, "high": 120.475, "low": 120.396, "volume": 23967}, {"date": "2023-11-27", "open": 120.379, "close": 120.37, "high": 120.432, "low": 120.336, "volume": 24923}, {"date": "2023-11-28", "open": 120.467, "close": 120.461, "high": 120.483, "low": 120.406, "volume": 27881}, {"date": "2023-11-29", "open": 120.461, "close": 120.424, "high": 120.504, "low": 120.423, "volume": 21159}, {"date": "2023-11-30", "open": 120.424, "close": 120.468, "high": 120.52, "low": 120.424, "volume": 24626}, {"date": "2023-12-01", "open": 120.472, "close": 120.578, "high": 120.626, "low": 120.472, "volume": 26517}, {"date": "2023-12-04", "open": 120.626, "close": 120.511, "high": 120.626, "low": 120.486, "volume": 24435}, {"date": "2023-12-05", "open": 120.509, "close": 120.516, "high": 120.527, "low": 120.473, "volume": 23659}, {"date": "2023-12-06", "open": 120.514, "close": 120.471, "high": 120.529, "low": 120.461, "volume": 29455}, {"date": "2023-12-07", "open": 120.513, "close": 120.517, "high": 120.555, "low": 120.447, "volume": 29052}, {"date": "2023-12-08", "open": 120.518, "close": 120.565, "high": 120.598, "low": 120.518, "volume": 24331}, {"date": "2023-12-11", "open": 120.624, "close": 120.793, "high": 120.824, "low": 120.624, "volume": 33476}, {"date": "2023-12-12", "open": 120.796, "close": 120.734, "high": 120.861, "low": 120.708, "volume": 43419}, {"date": "2023-12-13", "open": 120.784, "close": 120.886, "high": 121.062, "low": 120.784, "volume": 29601}, {"date": "2023-12-14", "open": 120.888, "close": 120.877, "high": 120.956, "low": 120.853, "volume": 33554}, {"date": "2023-12-15", "open": 120.877, "close": 120.956, "high": 120.959, "low": 120.838, "volume": 25558}, {"date": "2023-12-18", "open": 121.006, "close": 121.041, "high": 121.059, "low": 120.976, "volume": 25041}, {"date": "2023-12-19", "open": 121.017, "close": 121.053, "high": 121.075, "low": 120.972, "volume": 24880}, {"date": "2023-12-20", "open": 121.053, "close": 121.007, "high": 121.053, "low": 120.996, "volume": 35459}, {"date": "2023-12-21", "open": 120.996, "close": 121.062, "high": 121.147, "low": 120.939, "volume": 14636}, {"date": "2023-12-22", "open": 121.136, "close": 121.154, "high": 121.2, "low": 121.111, "volume": 5367}, {"date": "2023-12-25", "open": 121.187, "close": 121.256, "high": 121.276, "low": 121.129, "volume": 32568}, {"date": "2023-12-26", "open": 121.3, "close": 121.314, "high": 121.386, "low": 121.266, "volume": 26889}, {"date": "2023-12-27", "open": 121.364, "close": 121.412, "high": 121.457, "low": 121.358, "volume": 29288}, {"date": "2023-12-28", "open": 121.476, "close": 121.412, "high": 121.604, "low": 121.294, "volume": 6374}, {"date": "2023-12-29", "open": 121.46, "close": 121.638, "high": 121.651, "low": 121.46, "volume": 34607}, {"date": "2024-01-02", "open": 121.683, "close": 121.866, "high": 121.867, "low": 121.55, "volume": 26744}, {"date": "2024-01-03", "open": 121.851, "close": 121.547, "high": 121.885, "low": 121.537, "volume": 39898}, {"date": "2024-01-04", "open": 121.597, "close": 121.795, "high": 121.816, "low": 121.586, "volume": 3071}, {"date": "2024-01-05", "open": 121.797, "close": 122.153, "high": 122.155, "low": 121.697, "volume": 3544}, {"date": "2024-01-08", "open": 122.14, "close": 121.966, "high": 122.259, "low": 121.927, "volume": 26185}, {"date": "2024-01-09", "open": 121.951, "close": 122.118, "high": 122.136, "low": 121.925, "volume": 8244}, {"date": "2024-01-10", "open": 122.131, "close": 122.077, "high": 122.131, "low": 122.016, "volume": 16762}, {"date": "2024-01-11", "open": 122.02, "close": 121.998, "high": 122.063, "low": 121.92, "volume": 39070}, {"date": "2024-01-12", "open": 121.988, "close": 121.865, "high": 122.058, "low": 121.847, "volume": 27545}, {"date": "2024-01-15", "open": 121.846, "close": 121.884, "high": 121.889, "low": 121.809, "volume": 41671}, {"date": "2024-01-16", "open": 121.884, "close": 121.847, "high": 121.904, "low": 121.833, "volume": 24578}, {"date": "2024-01-17", "open": 121.846, "close": 121.994, "high": 121.995, "low": 121.827, "volume": 51466}, {"date": "2024-01-18", "open": 122.014, "close": 122.086, "high": 122.382, "low": 122.012, "volume": 12777}, {"date": "2024-01-19", "open": 122.076, "close": 122.152, "high": 122.191, "low": 122.038, "volume": 17694}, {"date": "2024-01-22", "open": 122.2, "close": 122.263, "high": 122.381, "low": 122.041, "volume": 15594}, {"date": "2024-01-23", "open": 122.272, "close": 122.202, "high": 122.292, "low": 122.136, "volume": 17570}, {"date": "2024-01-24", "open": 122.181, "close": 122.215, "high": 122.284, "low": 122.125, "volume": 30138}, {"date": "2024-01-25", "open": 122.181, "close": 122.225, "high": 122.246, "low": 122.092, "volume": 21893}, {"date": "2024-01-26", "open": 122.326, "close": 122.316, "high": 122.361, "low": 122.222, "volume": 16171}, {"date": "2024-01-29", "open": 122.298, "close": 122.386, "high": 122.436, "low": 122.278, "volume": 55107}, {"date": "2024-01-30", "open": 122.511, "close": 122.735, "high": 123.136, "low": 122.511, "volume": 19103}, {"date": "2024-01-31", "open": 123.027, "close": 122.94, "high": 123.036, "low": 122.791, "volume": 31097}, {"date": "2024-02-01", "open": 122.955, "close": 122.953, "high": 123.055, "low": 122.868, "volume": 59843}, {"date": "2024-02-02", "open": 122.953, "close": 122.926, "high": 122.953, "low": 122.869, "volume": 38222}, {"date": "2024-02-05", "open": 123.37, "close": 123.121, "high": 123.37, "low": 122.926, "volume": 10326}, {"date": "2024-02-06", "open": 123.096, "close": 122.793, "high": 123.102, "low": 122.73, "volume": 9362}, {"date": "2024-02-07", "open": 122.716, "close": 122.863, "high": 122.9, "low": 122.395, "volume": 13351}, {"date": "2024-02-08", "open": 123.144, "close": 123.036, "high": 123.144, "low": 122.843, "volume": 32701}, {"date": "2024-02-19", "open": 123.034, "close": 123.059, "high": 123.111, "low": 122.904, "volume": 20791}, {"date": "2024-02-20", "open": 123.057, "close": 123.145, "high": 123.216, "low": 123.013, "volume": 25068}, {"date": "2024-02-21", "open": 123.195, "close": 123.23, "high": 123.237, "low": 123.127, "volume": 34278}, {"date": "2024-02-22", "open": 123.236, "close": 123.207, "high": 123.245, "low": 123.17, "volume": 26613}, {"date": "2024-02-23", "open": 123.403, "close": 123.388, "high": 123.403, "low": 123.147, "volume": 35797}, {"date": "2024-02-26", "open": 123.39, "close": 123.489, "high": 123.518, "low": 123.36, "volume": 23867}, {"date": "2024-02-27", "open": 123.711, "close": 123.676, "high": 123.715, "low": 123.584, "volume": 24239}, {"date": "2024-02-28", "open": 123.572, "close": 123.838, "high": 124.036, "low": 123.562, "volume": 23738}, {"date": "2024-02-29", "open": 123.855, "close": 124.04, "high": 124.105, "low": 123.855, "volume": 19547}, {"date": "2024-03-01", "open": 123.826, "close": 123.574, "high": 124.085, "low": 123.536, "volume": 11630}, {"date": "2024-03-04", "open": 123.606, "close": 123.732, "high": 123.745, "low": 123.507, "volume": 17737}, {"date": "2024-03-05", "open": 123.739, "close": 123.759, "high": 123.798, "low": 123.717, "volume": 30650}, {"date": "2024-03-06", "open": 124.154, "close": 124.163, "high": 124.166, "low": 123.937, "volume": 28567}, {"date": "2024-03-07", "open": 124.442, "close": 124.297, "high": 124.5, "low": 124.037, "volume": 22069}, {"date": "2024-03-08", "open": 124.314, "close": 124.268, "high": 124.387, "low": 124.237, "volume": 28678}, {"date": "2024-03-11", "open": 124.267, "close": 124.141, "high": 124.31, "low": 124.136, "volume": 5301}, {"date": "2024-03-12", "open": 124.02, "close": 123.656, "high": 124.02, "low": 123.641, "volume": 32802}, {"date": "2024-03-13", "open": 123.639, "close": 123.606, "high": 123.639, "low": 123.19, "volume": 17813}, {"date": "2024-03-14", "open": 123.657, "close": 123.564, "high": 123.715, "low": 123.439, "volume": 39707}, {"date": "2024-03-15", "open": 123.658, "close": 123.71, "high": 123.755, "low": 123.586, "volume": 33055}, {"date": "2024-03-18", "open": 123.769, "close": 123.817, "high": 123.828, "low": 123.742, "volume": 81571}, {"date": "2024-03-19", "open": 123.965, "close": 124.101, "high": 124.112, "low": 123.888, "volume": 7550}, {"date": "2024-03-20", "open": 124.035, "close": 123.962, "high": 124.059, "low": 123.941, "volume": 35052}, {"date": "2024-03-21", "open": 123.936, "close": 123.962, "high": 124.009, "low": 123.736, "volume": 31154}, {"date": "2024-03-22", "open": 124.156, "close": 123.956, "high": 124.156, "low": 123.925, "volume": 21007}, {"date": "2024-03-25", "open": 123.913, "close": 123.781, "high": 123.926, "low": 123.715, "volume": 22923}, {"date": "2024-03-26", "open": 123.798, "close": 123.8, "high": 123.84, "low": 123.748, "volume": 24401}, {"date": "2024-03-27", "open": 123.822, "close": 123.886, "high": 123.906, "low": 123.767, "volume": 8001}, {"date": "2024-03-28", "open": 124.011, "close": 123.909, "high": 124.046, "low": 123.886, "volume": 3176}, {"date": "2024-03-29", "open": 123.919, "close": 124.05, "high": 124.07, "low": 123.851, "volume": 27951}, {"date": "2024-04-01", "open": 123.975, "close": 123.898, "high": 123.977, "low": 123.855, "volume": 26603}, {"date": "2024-04-02", "open": 123.954, "close": 123.952, "high": 123.977, "low": 123.898, "volume": 43906}, {"date": "2024-04-03", "open": 124.122, "close": 124.219, "high": 124.222, "low": 123.98, "volume": 30964}, {"date": "2024-04-08", "open": 124.237, "close": 124.271, "high": 124.301, "low": 124.107, "volume": 38908}, {"date": "2024-04-09", "open": 124.313, "close": 124.411, "high": 124.446, "low": 124.313, "volume": 40459}, {"date": "2024-04-10", "open": 124.373, "close": 124.314, "high": 124.378, "low": 124.189, "volume": 20866}, {"date": "2024-04-11", "open": 124.314, "close": 124.295, "high": 124.339, "low": 124.288, "volume": 35363}, {"date": "2024-04-12", "open": 124.399, "close": 124.53, "high": 124.561, "low": 124.399, "volume": 25054}, {"date": "2024-04-15", "open": 124.554, "close": 124.646, "high": 124.709, "low": 124.536, "volume": 31018}, {"date": "2024-04-16", "open": 124.646, "close": 124.657, "high": 124.659, "low": 124.581, "volume": 25675}, {"date": "2024-04-17", "open": 124.734, "close": 124.702, "high": 124.736, "low": 124.651, "volume": 26192}, {"date": "2024-04-18", "open": 124.717, "close": 124.921, "high": 124.931, "low": 124.716, "volume": 26489}, {"date": "2024-04-19", "open": 124.936, "close": 124.95, "high": 125.03, "low": 124.891, "volume": 44915}, {"date": "2024-04-22", "open": 124.967, "close": 125.038, "high": 125.041, "low": 124.925, "volume": 21973}, {"date": "2024-04-23", "open": 125.092, "close": 125.335, "high": 125.339, "low": 125.092, "volume": 37475}, {"date": "2024-04-24", "open": 125.058, "close": 124.763, "high": 125.335, "low": 124.693, "volume": 30050}, {"date": "2024-04-25", "open": 124.829, "close": 124.825, "high": 124.929, "low": 124.769, "volume": 25800}, {"date": "2024-04-26", "open": 124.89, "close": 124.529, "high": 124.924, "low": 124.524, "volume": 27039}, {"date": "2024-04-29", "open": 124.527, "close": 123.913, "high": 124.527, "low": 123.256, "volume": 8307}, {"date": "2024-04-30", "open": 124.026, "close": 124.38, "high": 124.385, "low": 124.026, "volume": 14715}, {"date": "2024-05-06", "open": 124.386, "close": 124.472, "high": 124.565, "low": 124.18, "volume": 8936}, {"date": "2024-05-07", "open": 124.632, "close": 124.791, "high": 124.841, "low": 124.476, "volume": 24421}, {"date": "2024-05-08", "open": 124.869, "close": 124.917, "high": 125.114, "low": 124.836, "volume": 21601}, {"date": "2024-05-09", "open": 124.799, "close": 124.736, "high": 124.825, "low": 124.711, "volume": 21054}, {"date": "2024-05-10", "open": 124.663, "close": 124.561, "high": 124.76, "low": 124.529, "volume": 22347}, {"date": "2024-05-13", "open": 124.685, "close": 124.826, "high": 124.826, "low": 124.661, "volume": 31535}, {"date": "2024-05-14", "open": 124.876, "close": 124.889, "high": 125.005, "low": 124.828, "volume": 33087}, {"date": "2024-05-15", "open": 124.89, "close": 124.8, "high": 124.965, "low": 124.781, "volume": 30460}, {"date": "2024-05-16", "open": 124.807, "close": 124.716, "high": 124.829, "low": 124.666, "volume": 21328}, {"date": "2024-05-17", "open": 124.525, "close": 124.546, "high": 124.628, "low": 124.516, "volume": 22128}, {"date": "2024-05-20", "open": 124.694, "close": 124.769, "high": 124.78, "low": 124.603, "volume": 11518}, {"date": "2024-05-21", "open": 124.769, "close": 124.687, "high": 124.811, "low": 124.676, "volume": 19371}, {"date": "2024-05-22", "open": 124.704, "close": 124.783, "high": 124.785, "low": 124.704, "volume": 28988}, {"date": "2024-05-23", "open": 124.867, "close": 124.927, "high": 124.931, "low": 124.788, "volume": 31996}, {"date": "2024-05-24", "open": 124.938, "close": 124.872, "high": 125.032, "low": 124.846, "volume": 28699}, {"date": "2024-05-27", "open": 124.867, "close": 124.85, "high": 124.867, "low": 124.788, "volume": 30207}, {"date": "2024-05-28", "open": 124.944, "close": 125.014, "high": 125.016, "low": 124.902, "volume": 27076}, {"date": "2024-05-29", "open": 125.124, "close": 125.12, "high": 125.136, "low": 125.047, "volume": 19026}, {"date": "2024-05-30", "open": 125.119, "close": 125.127, "high": 125.128, "low": 125.052, "volume": 24045}, {"date": "2024-05-31", "open": 124.903, "close": 124.934, "high": 124.956, "low": 124.827, "volume": 34730}, {"date": "2024-06-03", "open": 124.956, "close": 125.015, "high": 125.031, "low": 124.939, "volume": 48184}, {"date": "2024-06-04", "open": 125.074, "close": 125.024, "high": 125.106, "low": 124.968, "volume": 32298}, {"date": "2024-06-05", "open": 125.123, "close": 125.165, "high": 125.173, "low": 125.062, "volume": 31084}, {"date": "2024-06-06", "open": 125.248, "close": 125.202, "high": 125.29, "low": 125.167, "volume": 24210}, {"date": "2024-06-07", "open": 125.272, "close": 125.304, "high": 125.31, "low": 125.203, "volume": 16311}, {"date": "2024-06-11", "open": 125.304, "close": 125.322, "high": 125.363, "low": 125.295, "volume": 25506}, {"date": "2024-06-12", "open": 125.322, "close": 125.274, "high": 125.356, "low": 125.261, "volume": 22737}, {"date": "2024-06-13", "open": 125.358, "close": 125.37, "high": 125.371, "low": 125.282, "volume": 26028}, {"date": "2024-06-14", "open": 125.433, "close": 125.437, "high": 125.458, "low": 125.394, "volume": 19031}, {"date": "2024-06-17", "open": 125.498, "close": 125.508, "high": 125.521, "low": 125.459, "volume": 31515}, {"date": "2024-06-18", "open": 125.515, "close": 125.625, "high": 125.631, "low": 125.515, "volume": 17863}, {"date": "2024-06-19", "open": 125.601, "close": 125.648, "high": 125.681, "low": 125.536, "volume": 22137}, {"date": "2024-06-20", "open": 125.748, "close": 125.746, "high": 125.748, "low": 125.576, "volume": 20361}, {"date": "2024-06-21", "open": 125.739, "close": 125.645, "high": 125.739, "low": 125.584, "volume": 30436}, {"date": "2024-06-24", "open": 125.635, "close": 125.76, "high": 125.904, "low": 125.551, "volume": 24360}, {"date": "2024-06-25", "open": 125.789, "close": 125.9, "high": 125.924, "low": 125.789, "volume": 28968}, {"date": "2024-06-26", "open": 125.906, "close": 125.955, "high": 126.005, "low": 125.906, "volume": 23774}, {"date": "2024-06-27", "open": 125.945, "close": 126.12, "high": 126.136, "low": 125.945, "volume": 20317}, {"date": "2024-06-28", "open": 126.221, "close": 126.266, "high": 126.278, "low": 126.041, "volume": 27041}, {"date": "2024-07-01", "open": 126.287, "close": 125.856, "high": 126.506, "low": 125.706, "volume": 12577}, {"date": "2024-07-02", "open": 125.849, "close": 126.061, "high": 126.126, "low": 125.636, "volume": 45472}, {"date": "2024-07-03", "open": 126.077, "close": 126.172, "high": 126.213, "low": 126.041, "volume": 28451}, {"date": "2024-07-04", "open": 126.186, "close": 126.226, "high": 126.246, "low": 126.096, "volume": 27107}, {"date": "2024-07-05", "open": 126.214, "close": 125.986, "high": 126.214, "low": 125.906, "volume": 28176}, {"date": "2024-07-08", "open": 125.805, "close": 125.61, "high": 125.805, "low": 125.519, "volume": 32732}, {"date": "2024-07-09", "open": 125.83, "close": 125.928, "high": 125.929, "low": 125.83, "volume": 33922}, {"date": "2024-07-10", "open": 125.925, "close": 125.923, "high": 125.986, "low": 125.832, "volume": 43918}, {"date": "2024-07-11", "open": 125.964, "close": 126.008, "high": 126.037, "low": 125.901, "volume": 28394}, {"date": "2024-07-12", "open": 126.099, "close": 126.169, "high": 126.243, "low": 126.01, "volume": 25584}, {"date": "2024-07-15", "open": 126.174, "close": 126.276, "high": 126.316, "low": 126.172, "volume": 25521}, {"date": "2024-07-16", "open": 126.248, "close": 126.249, "high": 126.44, "low": 126.112, "volume": 77992}, {"date": "2024-07-17", "open": 126.281, "close": 126.391, "high": 126.399, "low": 126.281, "volume": 29061}, {"date": "2024-07-18", "open": 126.391, "close": 126.315, "high": 126.403, "low": 126.291, "volume": 24851}, {"date": "2024-07-19", "open": 126.364, "close": 126.345, "high": 126.415, "low": 126.294, "volume": 49162}, {"date": "2024-07-22", "open": 126.457, "close": 126.608, "high": 126.616, "low": 126.436, "volume": 27592}, {"date": "2024-07-23", "open": 126.671, "close": 126.842, "high": 126.865, "low": 126.67, "volume": 23110}, {"date": "2024-07-24", "open": 126.935, "close": 126.955, "high": 126.965, "low": 126.782, "volume": 29242}, {"date": "2024-07-25", "open": 126.943, "close": 126.972, "high": 127.115, "low": 126.924, "volume": 28174}, {"date": "2024-07-26", "open": 127.117, "close": 127.179, "high": 127.181, "low": 127.029, "volume": 11567}, {"date": "2024-07-29", "open": 127.181, "close": 127.275, "high": 127.296, "low": 127.181, "volume": 28253}, {"date": "2024-07-30", "open": 127.333, "close": 127.339, "high": 127.451, "low": 126.991, "volume": 26475}, {"date": "2024-07-31", "open": 127.426, "close": 127.492, "high": 127.621, "low": 127.355, "volume": 31216}, {"date": "2024-08-01", "open": 127.536, "close": 127.704, "high": 127.772, "low": 127.423, "volume": 22079}, {"date": "2024-08-02", "open": 127.814, "close": 127.721, "high": 127.877, "low": 127.552, "volume": 21258}, {"date": "2024-08-05", "open": 127.884, "close": 128.085, "high": 128.11, "low": 127.766, "volume": 36361}, {"date": "2024-08-06", "open": 127.539, "close": 127.65, "high": 127.799, "low": 127.496, "volume": 31532}, {"date": "2024-08-07", "open": 127.701, "close": 127.989, "high": 128.001, "low": 127.701, "volume": 26106}, {"date": "2024-08-08", "open": 127.788, "close": 127.561, "high": 127.904, "low": 127.477, "volume": 46754}, {"date": "2024-08-09", "open": 127.318, "close": 127.297, "high": 127.364, "low": 127.219, "volume": 40108}, {"date": "2024-08-12", "open": 126.852, "close": 126.448, "high": 127.126, "low": 126.447, "volume": 26159}, {"date": "2024-08-13", "open": 126.727, "close": 126.841, "high": 126.926, "low": 126.499, "volume": 30951}, {"date": "2024-08-14", "open": 127.103, "close": 127.265, "high": 127.4, "low": 127.056, "volume": 53196}, {"date": "2024-08-15", "open": 127.265, "close": 127.107, "high": 127.513, "low": 127.051, "volume": 21927}, {"date": "2024-08-16", "open": 127.214, "close": 127.224, "high": 127.296, "low": 127.086, "volume": 40975}, {"date": "2024-08-19", "open": 127.247, "close": 127.421, "high": 127.426, "low": 127.136, "volume": 51633}, {"date": "2024-08-20", "open": 127.423, "close": 127.368, "high": 127.432, "low": 127.324, "volume": 71388}, {"date": "2024-08-21", "open": 127.376, "close": 127.227, "high": 127.416, "low": 127.176, "volume": 28779}, {"date": "2024-08-22", "open": 127.394, "close": 127.492, "high": 127.514, "low": 127.292, "volume": 40233}, {"date": "2024-08-23", "open": 127.515, "close": 127.548, "high": 127.551, "low": 127.34, "volume": 28889}, {"date": "2024-08-26", "open": 127.549, "close": 127.557, "high": 127.62, "low": 127.444, "volume": 42598}, {"date": "2024-08-27", "open": 127.45, "close": 127.293, "high": 127.53, "low": 127.245, "volume": 32678}, {"date": "2024-08-28", "open": 127.305, "close": 127.449, "high": 127.508, "low": 127.181, "volume": 37396}, {"date": "2024-08-29", "open": 127.461, "close": 127.294, "high": 127.538, "low": 127.278, "volume": 29312}, {"date": "2024-08-30", "open": 127.343, "close": 127.278, "high": 127.377, "low": 127.109, "volume": 31459}, {"date": "2024-09-02", "open": 127.466, "close": 127.518, "high": 127.564, "low": 127.329, "volume": 48114}, {"date": "2024-09-03", "open": 127.58, "close": 127.683, "high": 127.716, "low": 127.487, "volume": 59773}, {"date": "2024-09-04", "open": 127.773, "close": 127.763, "high": 127.908, "low": 127.724, "volume": 29475}, {"date": "2024-09-05", "open": 127.898, "close": 127.906, "high": 127.966, "low": 127.837, "volume": 33566}, {"date": "2024-09-06", "open": 127.866, "close": 127.908, "high": 127.947, "low": 127.795, "volume": 35350}, {"date": "2024-09-09", "open": 127.907, "close": 128.008, "high": 128.018, "low": 127.852, "volume": 28140}, {"date": "2024-09-10", "open": 128.023, "close": 128.158, "high": 128.236, "low": 128.023, "volume": 34180}, {"date": "2024-09-11", "open": 128.167, "close": 128.335, "high": 128.373, "low": 128.167, "volume": 13963}, {"date": "2024-09-12", "open": 128.383, "close": 128.229, "high": 128.425, "low": 128.188, "volume": 21514}, {"date": "2024-09-13", "open": 128.453, "close": 128.483, "high": 128.501, "low": 128.342, "volume": 18432}, {"date": "2024-09-18", "open": 128.757, "close": 128.698, "high": 128.757, "low": 128.552, "volume": 22781}, {"date": "2024-09-19", "open": 128.917, "close": 128.62, "high": 128.933, "low": 128.598, "volume": 65667}, {"date": "2024-09-20", "open": 128.72, "close": 128.829, "high": 128.843, "low": 128.701, "volume": 36692}, {"date": "2024-09-23", "open": 128.866, "close": 128.894, "high": 128.951, "low": 128.816, "volume": 33961}, {"date": "2024-09-24", "open": 129.089, "close": 128.425, "high": 129.089, "low": 128.258, "volume": 29416}, {"date": "2024-09-25", "open": 128.405, "close": 128.842, "high": 128.845, "low": 127.766, "volume": 26274}, {"date": "2024-09-26", "open": 128.946, "close": 128.482, "high": 128.986, "low": 128.454, "volume": 23759}, {"date": "2024-09-27", "open": 127.886, "close": 127.399, "high": 128.086, "low": 126.837, "volume": 18146}, {"date": "2024-09-30", "open": 126.336, "close": 126.903, "high": 127.126, "low": 125.136, "volume": 40203}, {"date": "2024-10-08", "open": 125.81, "close": 127.077, "high": 127.331, "low": 125.81, "volume": 26626}, {"date": "2024-10-09", "open": 127.252, "close": 127.333, "high": 127.406, "low": 127.087, "volume": 37073}, {"date": "2024-10-10", "open": 127.333, "close": 127.901, "high": 127.904, "low": 127.137, "volume": 26151}, {"date": "2024-10-11", "open": 127.971, "close": 127.81, "high": 128.013, "low": 127.711, "volume": 39984}, {"date": "2024-10-14", "open": 127.924, "close": 127.82, "high": 127.936, "low": 127.786, "volume": 35037}, {"date": "2024-10-15", "open": 127.845, "close": 127.996, "high": 128.002, "low": 127.776, "volume": 55008}, {"date": "2024-10-16", "open": 128.026, "close": 127.993, "high": 128.133, "low": 127.908, "volume": 44518}, {"date": "2024-10-17", "open": 128.011, "close": 128.196, "high": 128.213, "low": 127.94, "volume": 83681}, {"date": "2024-10-18", "open": 128.439, "close": 128.137, "high": 128.439, "low": 127.964, "volume": 54058}, {"date": "2024-10-21", "open": 128.111, "close": 128.148, "high": 128.17, "low": 128.028, "volume": 39488}, {"date": "2024-10-22", "open": 128.149, "close": 128.065, "high": 128.203, "low": 128.041, "volume": 24857}, {"date": "2024-10-23", "open": 127.99, "close": 127.819, "high": 128.005, "low": 127.65, "volume": 20561}, {"date": "2024-10-24", "open": 127.887, "close": 127.776, "high": 127.964, "low": 127.756, "volume": 32137}, {"date": "2024-10-25", "open": 127.778, "close": 127.697, "high": 127.783, "low": 127.643, "volume": 32472}, {"date": "2024-10-28", "open": 127.791, "close": 127.642, "high": 127.791, "low": 127.617, "volume": 35595}, {"date": "2024-10-29", "open": 127.691, "close": 127.831, "high": 127.834, "low": 127.598, "volume": 21021}, {"date": "2024-10-30", "open": 127.836, "close": 127.822, "high": 127.876, "low": 127.762, "volume": 33875}, {"date": "2024-10-31", "open": 127.832, "close": 127.852, "high": 127.861, "low": 127.756, "volume": 31118}, {"date": "2024-11-01", "open": 127.886, "close": 128.055, "high": 128.089, "low": 127.886, "volume": 17388}, {"date": "2024-11-04", "open": 128.127, "close": 128.074, "high": 128.136, "low": 128.027, "volume": 30556}, {"date": "2024-11-05", "open": 128.136, "close": 128.13, "high": 128.141, "low": 128.035, "volume": 29311}, {"date": "2024-11-06", "open": 128.139, "close": 128.214, "high": 128.32, "low": 128.139, "volume": 16731}, {"date": "2024-11-07", "open": 128.265, "close": 128.242, "high": 128.318, "low": 128.214, "volume": 28861}, {"date": "2024-11-08", "open": 128.309, "close": 128.42, "high": 128.436, "low": 128.237, "volume": 25656}, {"date": "2024-11-11", "open": 128.466, "close": 128.46, "high": 128.502, "low": 128.439, "volume": 19907}, {"date": "2024-11-12", "open": 128.524, "close": 128.736, "high": 128.736, "low": 128.488, "volume": 24675}, {"date": "2024-11-13", "open": 128.732, "close": 128.724, "high": 128.813, "low": 128.666, "volume": 40699}, {"date": "2024-11-14", "open": 128.666, "close": 128.698, "high": 128.706, "low": 128.616, "volume": 27058}, {"date": "2024-11-15", "open": 128.721, "close": 128.761, "high": 128.806, "low": 128.666, "volume": 32713}, {"date": "2024-11-18", "open": 128.759, "close": 128.546, "high": 128.759, "low": 128.525, "volume": 67204}, {"date": "2024-11-19", "open": 128.536, "close": 128.603, "high": 128.661, "low": 128.426, "volume": 15297}, {"date": "2024-11-20", "open": 128.658, "close": 128.668, "high": 128.718, "low": 128.606, "volume": 49107}, {"date": "2024-11-21", "open": 128.675, "close": 128.819, "high": 128.826, "low": 128.654, "volume": 28920}, {"date": "2024-11-22", "open": 128.921, "close": 128.898, "high": 128.921, "low": 128.82, "volume": 35871}, {"date": "2024-11-25", "open": 128.863, "close": 129.062, "high": 129.087, "low": 128.855, "volume": 36088}, {"date": "2024-11-26", "open": 129.101, "close": 129.236, "high": 129.253, "low": 129.079, "volume": 28986}, {"date": "2024-11-27", "open": 129.203, "close": 129.111, "high": 129.29, "low": 129.103, "volume": 24380}, {"date": "2024-11-28", "open": 129.118, "close": 129.3, "high": 129.306, "low": 129.111, "volume": 19711}, {"date": "2024-11-29", "open": 129.396, "close": 129.445, "high": 129.498, "low": 129.239, "volume": 38416}, {"date": "2024-12-02", "open": 129.626, "close": 129.741, "high": 129.746, "low": 129.497, "volume": 36576}, {"date": "2024-12-03", "open": 129.813, "close": 129.852, "high": 129.886, "low": 129.763, "volume": 47640}, {"date": "2024-12-04", "open": 129.852, "close": 130.139, "high": 130.201, "low": 129.852, "volume": 32013}, {"date": "2024-12-05", "open": 130.089, "close": 130.267, "high": 130.306, "low": 129.952, "volume": 27693}, {"date": "2024-12-06", "open": 130.211, "close": 130.108, "high": 130.305, "low": 130.065, "volume": 81177}, {"date": "2024-12-09", "open": 130.14, "close": 130.274, "high": 130.279, "low": 130.13, "volume": 34133}, {"date": "2024-12-10", "open": 130.19, "close": 131.043, "high": 131.167, "low": 130.19, "volume": 71178}, {"date": "2024-12-11", "open": 130.976, "close": 131.264, "high": 131.283, "low": 130.803, "volume": 44283}, {"date": "2024-12-12", "open": 131.366, "close": 131.539, "high": 131.802, "low": 131.366, "volume": 53296}, {"date": "2024-12-13", "open": 131.902, "close": 132.013, "high": 132.068, "low": 131.659, "volume": 43913}, {"date": "2024-12-16", "open": 132.111, "close": 132.531, "high": 132.556, "low": 132.111, "volume": 42033}, {"date": "2024-12-17", "open": 132.286, "close": 132.243, "high": 132.346, "low": 132.136, "volume": 70465}, {"date": "2024-12-18", "open": 132.353, "close": 131.957, "high": 132.504, "low": 131.407, "volume": 95790}, {"date": "2024-12-19", "open": 131.974, "close": 131.823, "high": 132.087, "low": 131.736, "volume": 64289}, {"date": "2024-12-20", "open": 132.245, "close": 132.456, "high": 132.516, "low": 132.016, "volume": 154044}, {"date": "2024-12-23", "open": 132.913, "close": 132.635, "high": 132.932, "low": 132.486, "volume": 68047}, {"date": "2024-12-24", "open": 132.486, "close": 132.359, "high": 132.716, "low": 132.29, "volume": 59421}, {"date": "2024-12-25", "open": 132.4, "close": 132.209, "high": 132.439, "low": 132.014, "volume": 35740}, {"date": "2024-12-26", "open": 132.235, "close": 132.167, "high": 132.32, "low": 132.13, "volume": 37457}, {"date": "2024-12-27", "open": 132.391, "close": 132.642, "high": 132.661, "low": 132.39, "volume": 41241}, {"date": "2024-12-30", "open": 132.671, "close": 132.439, "high": 132.735, "low": 132.427, "volume": 16411}, {"date": "2024-12-31", "open": 132.765, "close": 132.69, "high": 132.798, "low": 132.591, "volume": 32170}, {"date": "2025-01-02", "open": 133.079, "close": 133.384, "high": 133.475, "low": 132.927, "volume": 45282}, {"date": "2025-01-03", "open": 133.751, "close": 133.705, "high": 133.858, "low": 133.343, "volume": 41041}, {"date": "2025-01-06", "open": 133.726, "close": 133.79, "high": 133.826, "low": 133.605, "volume": 36826}, {"date": "2025-01-07", "open": 133.716, "close": 133.613, "high": 133.759, "low": 133.584, "volume": 21061}, {"date": "2025-01-08", "open": 133.609, "close": 133.599, "high": 133.701, "low": 133.536, "volume": 35549}, {"date": "2025-01-09", "open": 133.667, "close": 133.416, "high": 133.677, "low": 133.406, "volume": 28454}, {"date": "2025-01-10", "open": 132.842, "close": 133.265, "high": 133.278, "low": 132.81, "volume": 45175}, {"date": "2025-01-13", "open": 133.22, "close": 133.193, "high": 133.286, "low": 133.035, "volume": 33461}, {"date": "2025-01-14", "open": 133.16, "close": 133.332, "high": 133.356, "low": 133.033, "volume": 23873}, {"date": "2025-01-15", "open": 133.478, "close": 133.579, "high": 133.642, "low": 133.446, "volume": 19924}, {"date": "2025-01-16", "open": 133.483, "close": 133.41, "high": 133.603, "low": 133.249, "volume": 36462}, {"date": "2025-01-17", "open": 133.477, "close": 133.322, "high": 133.535, "low": 133.282, "volume": 121518}, {"date": "2025-01-20", "open": 133.139, "close": 133.18, "high": 133.322, "low": 133.138, "volume": 85856}, {"date": "2025-01-21", "open": 133.166, "close": 133.295, "high": 133.365, "low": 133.146, "volume": 20866}, {"date": "2025-01-22", "open": 133.387, "close": 133.355, "high": 133.491, "low": 133.306, "volume": 111348}, {"date": "2025-01-23", "open": 133.348, "close": 133.287, "high": 133.348, "low": 133.201, "volume": 148631}, {"date": "2025-01-24", "open": 133.258, "close": 133.141, "high": 133.351, "low": 132.987, "volume": 156958}, {"date": "2025-01-27", "open": 133.276, "close": 133.65, "high": 133.671, "low": 133.266, "volume": 60612}, {"date": "2025-02-05", "open": 133.655, "close": 133.714, "high": 133.716, "low": 133.456, "volume": 155981}, {"date": "2025-02-06", "open": 133.766, "close": 133.795, "high": 133.839, "low": 133.668, "volume": 110820}, {"date": "2025-02-07", "open": 133.837, "close": 133.741, "high": 133.883, "low": 133.724, "volume": 153623}, {"date": "2025-02-10", "open": 133.672, "close": 133.61, "high": 133.674, "low": 133.576, "volume": 167378}, {"date": "2025-02-11", "open": 133.566, "close": 133.648, "high": 133.714, "low": 133.541, "volume": 62959}, {"date": "2025-02-12", "open": 133.694, "close": 133.646, "high": 133.699, "low": 133.606, "volume": 68662}, {"date": "2025-02-13", "open": 133.646, "close": 133.612, "high": 133.685, "low": 133.564, "volume": 133195}, {"date": "2025-02-14", "open": 133.581, "close": 133.398, "high": 133.583, "low": 133.326, "volume": 166831}, {"date": "2025-02-17", "open": 133.392, "close": 133.025, "high": 133.392, "low": 133.015, "volume": 29251}, {"date": "2025-02-18", "open": 133.002, "close": 132.897, "high": 133.079, "low": 132.536, "volume": 176844}, {"date": "2025-02-19", "open": 132.995, "close": 133.035, "high": 133.095, "low": 132.836, "volume": 173722}, {"date": "2025-02-20", "open": 133.042, "close": 132.9, "high": 133.061, "low": 132.7, "volume": 151282}, {"date": "2025-02-21", "open": 132.716, "close": 132.623, "high": 132.835, "low": 132.525, "volume": 163368}, {"date": "2025-02-24", "open": 132.442, "close": 132.026, "high": 132.531, "low": 131.907, "volume": 172149}, {"date": "2025-02-25", "open": 132.294, "close": 132.133, "high": 132.467, "low": 131.796, "volume": 28427}, {"date": "2025-02-26", "open": 132.251, "close": 132.482, "high": 132.593, "low": 132.251, "volume": 175506}, {"date": "2025-02-27", "open": 132.431, "close": 132.244, "high": 132.472, "low": 132.222, "volume": 185219}, {"date": "2025-02-28", "open": 132.236, "close": 132.451, "high": 133.236, "low": 132.086, "volume": 23356}, {"date": "2025-03-03", "open": 132.419, "close": 132.628, "high": 132.636, "low": 132.287, "volume": 166323}, {"date": "2025-03-04", "open": 132.731, "close": 132.581, "high": 132.889, "low": 132.506, "volume": 22262}, {"date": "2025-03-05", "open": 132.614, "close": 132.604, "high": 132.724, "low": 132.571, "volume": 155145}, {"date": "2025-03-06", "open": 132.506, "close": 132.265, "high": 132.515, "low": 132.213, "volume": 168750}, {"date": "2025-03-07", "open": 132.213, "close": 131.886, "high": 132.213, "low": 131.7, "volume": 29238}, {"date": "2025-03-10", "open": 131.678, "close": 131.591, "high": 131.925, "low": 131.536, "volume": 37935}, {"date": "2025-03-11", "open": 131.596, "close": 131.073, "high": 131.673, "low": 130.996, "volume": 27253}, {"date": "2025-03-12", "open": 130.936, "close": 131.582, "high": 131.636, "low": 130.657, "volume": 172291}, {"date": "2025-03-13", "open": 131.403, "close": 131.444, "high": 131.61, "low": 131.259, "volume": 29679}, {"date": "2025-03-14", "open": 131.291, "close": 131.237, "high": 131.418, "low": 131.016, "volume": 37399}, {"date": "2025-03-17", "open": 131.102, "close": 130.835, "high": 131.154, "low": 130.802, "volume": 23726}, {"date": "2025-03-18", "open": 130.786, "close": 130.818, "high": 130.981, "low": 130.717, "volume": 28981}, {"date": "2025-03-19", "open": 130.914, "close": 130.933, "high": 131.016, "low": 130.88, "volume": 15617}, {"date": "2025-03-20", "open": 131.136, "close": 131.487, "high": 131.568, "low": 131.136, "volume": 31390}, {"date": "2025-03-21", "open": 131.539, "close": 131.485, "high": 131.568, "low": 131.34, "volume": 22759}, {"date": "2025-03-24", "open": 131.404, "close": 131.338, "high": 131.439, "low": 131.225, "volume": 107852}, {"date": "2025-03-25", "open": 131.709, "close": 131.658, "high": 131.727, "low": 131.579, "volume": 58093}, {"date": "2025-03-26", "open": 131.557, "close": 131.768, "high": 131.788, "low": 131.405, "volume": 18606}, {"date": "2025-03-27", "open": 131.76, "close": 131.822, "high": 131.851, "low": 131.725, "volume": 26822}, {"date": "2025-03-28", "open": 131.712, "close": 131.643, "high": 131.821, "low": 131.636, "volume": 24064}, {"date": "2025-03-31", "open": 131.637, "close": 131.625, "high": 131.793, "low": 131.594, "volume": 33028}, {"date": "2025-04-01", "open": 131.687, "close": 131.645, "high": 131.772, "low": 131.547, "volume": 36362}, {"date": "2025-04-02", "open": 131.66, "close": 131.838, "high": 131.856, "low": 131.649, "volume": 43622}, {"date": "2025-04-03", "open": 132.435, "close": 132.654, "high": 132.682, "low": 132.13, "volume": 33503}, {"date": "2025-04-07", "open": 133.633, "close": 133.534, "high": 133.633, "low": 133.156, "volume": 38428}, {"date": "2025-04-08", "open": 133.261, "close": 133.129, "high": 133.349, "low": 133.054, "volume": 54515}, {"date": "2025-04-09", "open": 133.256, "close": 133.228, "high": 133.474, "low": 133.136, "volume": 30589}, {"date": "2025-04-10", "open": 133.136, "close": 133.243, "high": 133.276, "low": 132.838, "volume": 74001}, {"date": "2025-04-11", "open": 133.365, "close": 133.22, "high": 133.429, "low": 133.157, "volume": 27658}, {"date": "2025-04-14", "open": 133.133, "close": 133.22, "high": 133.224, "low": 132.988, "volume": 165458}, {"date": "2025-04-15", "open": 133.24, "close": 133.313, "high": 133.329, "low": 133.22, "volume": 73978}, {"date": "2025-04-16", "open": 133.353, "close": 133.495, "high": 133.536, "low": 133.353, "volume": 162333}, {"date": "2025-04-17", "open": 133.496, "close": 133.461, "high": 133.533, "low": 133.417, "volume": 182426}, {"date": "2025-04-18", "open": 133.45, "close": 133.384, "high": 133.515, "low": 133.316, "volume": 162689}, {"date": "2025-04-21", "open": 133.382, "close": 133.243, "high": 133.384, "low": 133.234, "volume": 25386}, {"date": "2025-04-22", "open": 133.274, "close": 133.375, "high": 133.376, "low": 133.274, "volume": 40676}, {"date": "2025-04-23", "open": 133.265, "close": 133.236, "high": 133.274, "low": 133.121, "volume": 30394}, {"date": "2025-04-24", "open": 133.307, "close": 133.154, "high": 133.321, "low": 133.139, "volume": 93908}, {"date": "2025-04-25", "open": 133.236, "close": 133.232, "high": 133.293, "low": 133.164, "volume": 125705}, {"date": "2025-04-28", "open": 133.278, "close": 133.322, "high": 133.354, "low": 133.253, "volume": 40502}, {"date": "2025-04-29", "open": 133.426, "close": 133.638, "high": 133.66, "low": 133.4, "volume": 29479}, {"date": "2025-04-30", "open": 133.576, "close": 133.682, "high": 133.712, "low": 133.533, "volume": 25847}, {"date": "2025-05-06", "open": 133.656, "close": 133.636, "high": 133.686, "low": 133.557, "volume": 16319}, {"date": "2025-05-07", "open": 133.698, "close": 133.522, "high": 133.698, "low": 133.427, "volume": 141903}, {"date": "2025-05-08", "open": 133.57, "close": 133.63, "high": 133.764, "low": 133.57, "volume": 92664}, {"date": "2025-05-09", "open": 133.686, "close": 133.728, "high": 133.756, "low": 133.666, "volume": 169586}, {"date": "2025-05-12", "open": 133.615, "close": 133.59, "high": 133.699, "low": 133.478, "volume": 20109}, {"date": "2025-05-13", "open": 133.328, "close": 133.42, "high": 133.435, "low": 133.136, "volume": 26176}, {"date": "2025-05-14", "open": 133.446, "close": 133.311, "high": 133.451, "low": 133.286, "volume": 147480}, {"date": "2025-05-15", "open": 133.319, "close": 133.285, "high": 133.364, "low": 133.259, "volume": 24552}, {"date": "2025-05-16", "open": 133.181, "close": 133.184, "high": 133.268, "low": 133.137, "volume": 19687}, {"date": "2025-05-19", "open": 133.204, "close": 133.26, "high": 133.274, "low": 133.184, "volume": 113339}, {"date": "2025-05-20", "open": 133.376, "close": 133.341, "high": 133.389, "low": 133.287, "volume": 72267}, {"date": "2025-05-21", "open": 133.344, "close": 133.385, "high": 133.39, "low": 133.319, "volume": 25837}, {"date": "2025-05-22", "open": 133.351, "close": 133.346, "high": 133.391, "low": 133.321, "volume": 21383}, {"date": "2025-05-23", "open": 133.296, "close": 133.339, "high": 133.346, "low": 133.21, "volume": 23457}, {"date": "2025-05-26", "open": 133.418, "close": 133.364, "high": 133.418, "low": 133.32, "volume": 42036}, {"date": "2025-05-27", "open": 133.353, "close": 133.322, "high": 133.376, "low": 133.305, "volume": 28655}, {"date": "2025-05-28", "open": 133.298, "close": 133.281, "high": 133.332, "low": 133.257, "volume": 9807}, {"date": "2025-05-29", "open": 133.207, "close": 133.144, "high": 133.298, "low": 133.108, "volume": 39526}, {"date": "2025-05-30", "open": 133.276, "close": 133.26, "high": 133.295, "low": 133.201, "volume": 156779}, {"date": "2025-06-03", "open": 133.325, "close": 133.282, "high": 133.325, "low": 133.221, "volume": 104790}, {"date": "2025-06-04", "open": 133.35, "close": 133.333, "high": 133.35, "low": 133.28, "volume": 19519}, {"date": "2025-06-05", "open": 133.334, "close": 133.366, "high": 133.402, "low": 133.279, "volume": 107259}, {"date": "2025-06-06", "open": 133.436, "close": 133.475, "high": 133.477, "low": 133.395, "volume": 153549}, {"date": "2025-06-09", "open": 133.591, "close": 133.633, "high": 133.676, "low": 133.483, "volume": 292156}, {"date": "2025-06-10", "open": 133.64, "close": 133.687, "high": 133.705, "low": 133.64, "volume": 562360}, {"date": "2025-06-11", "open": 133.737, "close": 133.798, "high": 133.816, "low": 133.703, "volume": 365515}, {"date": "2025-06-12", "open": 133.814, "close": 133.789, "high": 133.818, "low": 133.735, "volume": 457896}, {"date": "2025-06-13", "open": 133.789, "close": 133.783, "high": 133.836, "low": 133.726, "volume": 338833}, {"date": "2025-06-16", "open": 133.791, "close": 133.816, "high": 133.831, "low": 133.754, "volume": 342682}, {"date": "2025-06-17", "open": 133.824, "close": 133.947, "high": 133.956, "low": 133.774, "volume": 559023}, {"date": "2025-06-18", "open": 133.936, "close": 133.939, "high": 133.956, "low": 133.881, "volume": 605922}, {"date": "2025-06-19", "open": 134.012, "close": 133.965, "high": 134.012, "low": 133.926, "volume": 688683}, {"date": "2025-06-20", "open": 133.896, "close": 133.999, "high": 134.002, "low": 133.896, "volume": 819505}, {"date": "2025-06-23", "open": 133.999, "close": 133.968, "high": 134.039, "low": 133.966, "volume": 406761}, {"date": "2025-06-24", "open": 133.964, "close": 133.909, "high": 133.964, "low": 133.905, "volume": 688229}, {"date": "2025-06-25", "open": 133.836, "close": 133.786, "high": 133.953, "low": 133.778, "volume": 562944}, {"date": "2025-06-26", "open": 133.777, "close": 133.787, "high": 133.836, "low": 133.736, "volume": 179274}, {"date": "2025-06-27", "open": 133.81, "close": 133.92, "high": 133.926, "low": 133.799, "volume": 600212}, {"date": "2025-06-30", "open": 133.886, "close": 133.772, "high": 133.886, "low": 133.771, "volume": 303264}, {"date": "2025-07-01", "open": 133.805, "close": 133.864, "high": 133.864, "low": 133.795, "volume": 380392}, {"date": "2025-07-02", "open": 133.933, "close": 134.016, "high": 134.016, "low": 133.924, "volume": 642623}, {"date": "2025-07-03", "open": 134.016, "close": 134.04, "high": 134.055, "low": 133.97, "volume": 608899}, {"date": "2025-07-04", "open": 134.051, "close": 134.059, "high": 134.084, "low": 134.027, "volume": 529157}, {"date": "2025-07-07", "open": 134.039, "close": 134.074, "high": 134.08, "low": 134.039, "volume": 561853}, {"date": "2025-07-08", "open": 134.073, "close": 134.003, "high": 134.073, "low": 133.968, "volume": 379431}, {"date": "2025-07-09", "open": 133.976, "close": 133.968, "high": 134.085, "low": 133.936, "volume": 304051}, {"date": "2025-07-10", "open": 133.993, "close": 133.796, "high": 133.993, "low": 133.746, "volume": 538806}, {"date": "2025-07-11", "open": 133.791, "close": 133.744, "high": 133.818, "low": 133.627, "volume": 233512}, {"date": "2025-07-14", "open": 133.714, "close": 133.641, "high": 133.714, "low": 133.544, "volume": 233196}, {"date": "2025-07-15", "open": 133.734, "close": 133.873, "high": 133.886, "low": 133.691, "volume": 398381}, {"date": "2025-07-16", "open": 133.903, "close": 133.884, "high": 133.934, "low": 133.836, "volume": 621008}, {"date": "2025-07-17", "open": 133.884, "close": 133.883, "high": 133.914, "low": 133.816, "volume": 455440}, {"date": "2025-07-18", "open": 133.866, "close": 133.802, "high": 133.866, "low": 133.761, "volume": 749791}, {"date": "2025-07-21", "open": 133.786, "close": 133.676, "high": 133.786, "low": 133.592, "volume": 454465}, {"date": "2025-07-22", "open": 133.702, "close": 133.545, "high": 133.749, "low": 133.541, "volume": 596709}, {"date": "2025-07-23", "open": 133.438, "close": 133.48, "high": 133.544, "low": 133.237, "volume": 311357}, {"date": "2025-07-24", "open": 133.417, "close": 133.135, "high": 133.417, "low": 133.132, "volume": 556043}, {"date": "2025-07-25", "open": 133.107, "close": 132.96, "high": 133.207, "low": 132.957, "volume": 237392}, {"date": "2025-07-28", "open": 133.255, "close": 133.309, "high": 133.333, "low": 133.077, "volume": 376467}, {"date": "2025-07-29", "open": 133.196, "close": 132.993, "high": 133.304, "low": 132.986, "volume": 549107}, {"date": "2025-07-30", "open": 133.084, "close": 133.219, "high": 133.23, "low": 132.906, "volume": 214600}, {"date": "2025-07-31", "open": 133.329, "close": 133.482, "high": 133.494, "low": 133.276, "volume": 399151}, {"date": "2025-08-01", "open": 133.389, "close": 133.478, "high": 133.556, "low": 133.286, "volume": 520269}, {"date": "2025-08-04", "open": 133.566, "close": 133.481, "high": 133.666, "low": 133.466, "volume": 485940}, {"date": "2025-08-05", "open": 133.477, "close": 133.497, "high": 133.532, "low": 133.374, "volume": 354105}, {"date": "2025-08-06", "open": 133.501, "close": 133.575, "high": 133.596, "low": 133.476, "volume": 489485}, {"date": "2025-08-07", "open": 133.639, "close": 133.614, "high": 133.696, "low": 133.546, "volume": 437989}, {"date": "2025-08-08", "open": 133.706, "close": 133.667, "high": 133.706, "low": 133.593, "volume": 658046}, {"date": "2025-08-11", "open": 133.687, "close": 133.398, "high": 133.689, "low": 133.386, "volume": 511344}, {"date": "2025-08-12", "open": 133.341, "close": 133.29, "high": 133.465, "low": 133.208, "volume": 190842}, {"date": "2025-08-13", "open": 133.246, "close": 133.356, "high": 133.37, "low": 133.163, "volume": 552991}, {"date": "2025-08-14", "open": 133.386, "close": 133.208, "high": 133.386, "low": 133.129, "volume": 192586}, {"date": "2025-08-15", "open": 133.326, "close": 133.182, "high": 133.326, "low": 133.163, "volume": 515098}, {"date": "2025-08-18", "open": 133.058, "close": 132.699, "high": 133.126, "low": 132.647, "volume": 211584}, {"date": "2025-08-19", "open": 132.718, "close": 132.757, "high": 132.801, "low": 132.636, "volume": 343474}, {"date": "2025-08-20", "open": 132.884, "close": 132.625, "high": 132.94, "low": 132.579, "volume": 783200}, {"date": "2025-08-21", "open": 132.67, "close": 132.656, "high": 132.686, "low": 132.478, "volume": 294586}, {"date": "2025-08-22", "open": 132.709, "close": 132.605, "high": 132.846, "low": 132.566, "volume": 90271}, {"date": "2025-08-25", "open": 132.651, "close": 132.82, "high": 132.876, "low": 132.566, "volume": 198559}, {"date": "2025-08-26", "open": 132.952, "close": 132.911, "high": 132.972, "low": 132.816, "volume": 169666}, {"date": "2025-08-27", "open": 132.911, "close": 133.001, "high": 133.006, "low": 132.837, "volume": 179199}, {"date": "2025-08-28", "open": 133.001, "close": 132.704, "high": 133.001, "low": 132.696, "volume": 247614}, {"date": "2025-08-29", "open": 132.744, "close": 132.748, "high": 132.822, "low": 132.69, "volume": 590411}, {"date": "2025-09-01", "open": 132.746, "close": 132.855, "high": 132.868, "low": 132.698, "volume": 383547}, {"date": "2025-09-02", "open": 132.869, "close": 132.862, "high": 132.912, "low": 132.791, "volume": 209460}, {"date": "2025-09-03", "open": 132.926, "close": 132.976, "high": 133.016, "low": 132.866, "volume": 409815}, {"date": "2025-09-04", "open": 133.046, "close": 133.256, "high": 133.313, "low": 133.038, "volume": 286688}, {"date": "2025-09-05", "open": 133.206, "close": 132.867, "high": 133.206, "low": 132.826, "volume": 240853}, {"date": "2025-09-08", "open": 132.836, "close": 132.733, "high": 132.848, "low": 132.699, "volume": 202174}, {"date": "2025-09-09", "open": 132.766, "close": 132.667, "high": 132.787, "low": 132.647, "volume": 242319}, {"date": "2025-09-10", "open": 132.655, "close": 132.365, "high": 132.681, "low": 132.321, "volume": 320109}, {"date": "2025-09-11", "open": 132.456, "close": 132.437, "high": 132.53, "low": 132.256, "volume": 172163}, {"date": "2025-09-12", "open": 132.369, "close": 132.661, "high": 132.691, "low": 132.369, "volume": 232527}, {"date": "2025-09-15", "open": 132.737, "close": 132.759, "high": 132.786, "low": 132.669, "volume": 347952}, {"date": "2025-09-16", "open": 132.746, "close": 132.823, "high": 132.862, "low": 132.486, "volume": 308135}, {"date": "2025-09-17", "open": 132.911, "close": 133.002, "high": 133.024, "low": 132.802, "volume": 362383}, {"date": "2025-09-18", "open": 132.975, "close": 132.974, "high": 133.002, "low": 132.871, "volume": 310865}, {"date": "2025-09-19", "open": 132.998, "close": 132.787, "high": 133.062, "low": 132.683, "volume": 215367}, {"date": "2025-09-22", "open": 132.76, "close": 132.796, "high": 132.994, "low": 132.747, "volume": 86876}, {"date": "2025-09-23", "open": 132.786, "close": 132.621, "high": 132.803, "low": 132.527, "volume": 311727}, {"date": "2025-09-24", "open": 132.751, "close": 132.404, "high": 132.751, "low": 132.376, "volume": 337717}, {"date": "2025-09-25", "open": 132.405, "close": 132.362, "high": 132.405, "low": 132.136, "volume": 133457}, {"date": "2025-09-26", "open": 132.486, "close": 132.555, "high": 132.594, "low": 132.425, "volume": 59440}, {"date": "2025-09-29", "open": 132.585, "close": 132.49, "high": 132.632, "low": 132.392, "volume": 243711}, {"date": "2025-09-30", "open": 132.664, "close": 132.75, "high": 132.781, "low": 132.52, "volume": 147995}, {"date": "2025-10-09", "open": 132.826, "close": 132.88, "high": 132.933, "low": 132.698, "volume": 326256}, {"date": "2025-10-10", "open": 132.944, "close": 132.811, "high": 132.995, "low": 132.796, "volume": 253625}, {"date": "2025-10-13", "open": 133.012, "close": 132.943, "high": 133.076, "low": 132.827, "volume": 291334}, {"date": "2025-10-14", "open": 132.886, "close": 133.175, "high": 133.178, "low": 132.803, "volume": 390591}, {"date": "2025-10-15", "open": 133.186, "close": 133.105, "high": 133.186, "low": 133.053, "volume": 331538}, {"date": "2025-10-16", "open": 133.176, "close": 133.21, "high": 133.222, "low": 133.106, "volume": 248718}, {"date": "2025-10-17", "open": 133.265, "close": 133.422, "high": 133.423, "low": 133.25, "volume": 256402}, {"date": "2025-10-20", "open": 133.404, "close": 133.175, "high": 133.404, "low": 133.13, "volume": 408612}, {"date": "2025-10-21", "open": 133.096, "close": 133.167, "high": 133.193, "low": 133.085, "volume": 401996}, {"date": "2025-10-22", "open": 133.233, "close": 133.182, "high": 133.233, "low": 133.111, "volume": 404081}, {"date": "2025-10-23", "open": 133.257, "close": 133.082, "high": 133.257, "low": 133.074, "volume": 337832}, {"date": "2025-10-24", "open": 133.072, "close": 133.018, "high": 133.097, "low": 133.01, "volume": 485577}, {"date": "2025-10-27", "open": 132.976, "close": 133.168, "high": 133.185, "low": 132.916, "volume": 672103}, {"date": "2025-10-28", "open": 133.396, "close": 133.555, "high": 133.575, "low": 133.351, "volume": 493251}, {"date": "2025-10-29", "open": 133.554, "close": 133.555, "high": 133.613, "low": 133.452, "volume": 694760}, {"date": "2025-10-30", "open": 133.555, "close": 133.701, "high": 133.723, "low": 133.498, "volume": 504358}, {"date": "2025-10-31", "open": 133.745, "close": 133.783, "high": 133.824, "low": 133.705, "volume": 347486}, {"date": "2025-11-03", "open": 133.783, "close": 133.802, "high": 133.815, "low": 133.749, "volume": 600315}, {"date": "2025-11-04", "open": 133.856, "close": 133.85, "high": 133.856, "low": 133.777, "volume": 542653}, {"date": "2025-11-05", "open": 133.949, "close": 133.848, "high": 133.999, "low": 133.825, "volume": 302820}, {"date": "2025-11-06", "open": 133.839, "close": 133.708, "high": 133.855, "low": 133.668, "volume": 561481}, {"date": "2025-11-07", "open": 133.749, "close": 133.682, "high": 133.766, "low": 133.669, "volume": 437542}, {"date": "2025-11-10", "open": 133.646, "close": 133.629, "high": 133.695, "low": 133.595, "volume": 603336}, {"date": "2025-11-11", "open": 133.656, "close": 133.554, "high": 133.679, "low": 133.551, "volume": 451815}, {"date": "2025-11-12", "open": 133.596, "close": 133.657, "high": 133.665, "low": 133.559, "volume": 601692}, {"date": "2025-11-13", "open": 133.657, "close": 133.563, "high": 133.66, "low": 133.53, "volume": 395819}, {"date": "2025-11-14", "open": 133.586, "close": 133.637, "high": 133.641, "low": 133.576, "volume": 295203}, {"date": "2025-11-17", "open": 133.679, "close": 133.749, "high": 133.763, "low": 133.638, "volume": 82844}, {"date": "2025-11-18", "open": 133.812, "close": 133.779, "high": 133.815, "low": 133.718, "volume": 441348}, {"date": "2025-11-19", "open": 133.661, "close": 133.724, "high": 133.76, "low": 133.661, "volume": 327844}, {"date": "2025-11-20", "open": 133.682, "close": 133.76, "high": 133.782, "low": 133.682, "volume": 390089}, {"date": "2025-11-21", "open": 133.764, "close": 133.733, "high": 133.806, "low": 133.677, "volume": 245943}, {"date": "2025-11-24", "open": 133.723, "close": 133.747, "high": 133.77, "low": 133.663, "volume": 157044}, {"date": "2025-11-25", "open": 133.731, "close": 133.627, "high": 133.734, "low": 133.616, "volume": 468376}, {"date": "2025-11-26", "open": 133.631, "close": 133.321, "high": 133.633, "low": 133.318, "volume": 173995}, {"date": "2025-11-27", "open": 133.446, "close": 133.336, "high": 133.446, "low": 133.315, "volume": 163665}, {"date": "2025-11-28", "open": 133.367, "close": 133.357, "high": 133.393, "low": 133.283, "volume": 319677}, {"date": "2025-12-01", "open": 133.396, "close": 133.477, "high": 133.492, "low": 133.301, "volume": 190596}, {"date": "2025-12-02", "open": 133.495, "close": 133.4, "high": 133.495, "low": 133.381, "volume": 434557}, {"date": "2025-12-03", "open": 133.416, "close": 133.465, "high": 133.494, "low": 133.4, "volume": 371634}, {"date": "2025-12-04", "open": 133.296, "close": 133.044, "high": 133.346, "low": 133.037, "volume": 68794}, {"date": "2025-12-05", "open": 133.101, "close": 133.279, "high": 133.331, "low": 133.09, "volume": 493386}, {"date": "2025-12-08", "open": 133.296, "close": 133.273, "high": 133.356, "low": 133.18, "volume": 494488}, {"date": "2025-12-09", "open": 133.416, "close": 133.475, "high": 133.484, "low": 133.337, "volume": 326353}, {"date": "2025-12-10", "open": 133.392, "close": 133.468, "high": 133.555, "low": 133.392, "volume": 343113}, {"date": "2025-12-11", "open": 133.532, "close": 133.601, "high": 133.612, "low": 133.497, "volume": 299099}, {"date": "2025-12-12", "open": 133.694, "close": 133.508, "high": 133.694, "low": 133.44, "volume": 197207}, {"date": "2025-12-15", "open": 133.374, "close": 133.235, "high": 133.47, "low": 133.18, "volume": 102888}, {"date": "2025-12-16", "open": 133.23, "close": 133.255, "high": 133.327, "low": 133.209, "volume": 363226}, {"date": "2025-12-17", "open": 133.455, "close": 133.407, "high": 133.455, "low": 133.303, "volume": 349912}, {"date": "2025-12-18", "open": 133.346, "close": 133.437, "high": 133.507, "low": 133.145, "volume": 467631}, {"date": "2025-12-19", "open": 133.474, "close": 133.521, "high": 133.522, "low": 133.435, "volume": 350459}, {"date": "2025-12-22", "open": 133.567, "close": 133.389, "high": 133.569, "low": 133.332, "volume": 185824}, {"date": "2025-12-23", "open": 133.412, "close": 133.71, "high": 133.739, "low": 133.336, "volume": 386210}, {"date": "2025-12-24", "open": 133.598, "close": 133.63, "high": 133.696, "low": 133.598, "volume": 472718}, {"date": "2025-12-25", "open": 133.695, "close": 133.672, "high": 133.696, "low": 133.637, "volume": 491143}, {"date": "2025-12-26", "open": 133.679, "close": 133.604, "high": 133.717, "low": 133.572, "volume": 457391}, {"date": "2025-12-29", "open": 133.601, "close": 133.197, "high": 133.601, "low": 133.13, "volume": 62189}, {"date": "2025-12-30", "open": 133.251, "close": 133.142, "high": 133.276, "low": 133.079, "volume": 402847}, {"date": "2025-12-31", "open": 133.18, "close": 133.157, "high": 133.222, "low": 132.992, "volume": 536951}, {"date": "2026-01-05", "open": 133.235, "close": 133.072, "high": 133.238, "low": 133.053, "volume": 524170}, {"date": "2026-01-06", "open": 133.029, "close": 132.89, "high": 133.029, "low": 132.84, "volume": 190074}, {"date": "2026-01-07", "open": 132.867, "close": 132.857, "high": 132.967, "low": 132.757, "volume": 386045}, {"date": "2026-01-08", "open": 132.862, "close": 133.063, "high": 133.073, "low": 132.855, "volume": 208953}, {"date": "2026-01-09", "open": 133.127, "close": 133.189, "high": 133.239, "low": 133.017, "volume": 57046}, {"date": "2026-01-12", "open": 133.189, "close": 133.202, "high": 133.3, "low": 133.102, "volume": 34103}, {"date": "2026-01-13", "open": 133.149, "close": 133.315, "high": 133.339, "low": 133.149, "volume": 31188}, {"date": "2026-01-14", "open": 133.386, "close": 133.373, "high": 133.389, "low": 133.222, "volume": 325177}, {"date": "2026-01-15", "open": 133.436, "close": 133.476, "high": 133.622, "low": 133.379, "volume": 156128}, {"date": "2026-01-16", "open": 133.495, "close": 133.561, "high": 133.595, "low": 133.41, "volume": 48058}, {"date": "2026-01-19", "open": 133.654, "close": 133.595, "high": 133.657, "low": 133.532, "volume": 331370}, {"date": "2026-01-20", "open": 133.629, "close": 133.856, "high": 133.878, "low": 133.596, "volume": 355575}, {"date": "2026-01-21", "open": 133.761, "close": 133.979, "high": 134.003, "low": 133.761, "volume": 242783}, {"date": "2026-01-22", "open": 133.959, "close": 133.905, "high": 133.959, "low": 133.863, "volume": 279631}, {"date": "2026-01-23", "open": 133.86, "close": 133.906, "high": 133.986, "low": 133.851, "volume": 535324}, {"date": "2026-01-26", "open": 133.934, "close": 133.963, "high": 134.023, "low": 133.811, "volume": 77686}, {"date": "2026-01-27", "open": 133.951, "close": 133.914, "high": 134.009, "low": 133.846, "volume": 526870}, {"date": "2026-01-28", "open": 133.924, "close": 133.999, "high": 134.007, "low": 133.876, "volume": 458023}, {"date": "2026-01-29", "open": 134.099, "close": 134.059, "high": 134.205, "low": 134.039, "volume": 432636}, {"date": "2026-01-30", "open": 134.055, "close": 134.122, "high": 134.223, "low": 134.055, "volume": 494424}, {"date": "2026-02-02", "open": 134.125, "close": 134.129, "high": 134.225, "low": 134.081, "volume": 416748}, {"date": "2026-02-03", "open": 134.128, "close": 134.109, "high": 134.129, "low": 134.034, "volume": 445546}, {"date": "2026-02-04", "open": 134.122, "close": 134.061, "high": 134.139, "low": 133.625, "volume": 564512}, {"date": "2026-02-05", "open": 134.125, "close": 134.245, "high": 134.247, "low": 134.044, "volume": 292821}, {"date": "2026-02-06", "open": 134.341, "close": 134.356, "high": 134.373, "low": 134.272, "volume": 401436}, {"date": "2026-02-09", "open": 134.272, "close": 134.414, "high": 134.414, "low": 134.271, "volume": 470738}, {"date": "2026-02-10", "open": 134.41, "close": 134.445, "high": 134.462, "low": 134.382, "volume": 554809}, {"date": "2026-02-11", "open": 134.469, "close": 134.533, "high": 134.554, "low": 134.468, "volume": 142699}, {"date": "2026-02-12", "open": 134.587, "close": 134.637, "high": 134.655, "low": 134.529, "volume": 20748}, {"date": "2026-02-13", "open": 134.715, "close": 134.587, "high": 134.728, "low": 134.469, "volume": 61125}, {"date": "2026-02-24", "open": 134.58, "close": 134.576, "high": 134.627, "low": 134.551, "volume": 255689}, {"date": "2026-02-25", "open": 134.586, "close": 134.36, "high": 134.618, "low": 134.342, "volume": 274135}, {"date": "2026-02-26", "open": 134.359, "close": 134.18, "high": 134.359, "low": 134.142, "volume": 79145}, {"date": "2026-02-27", "open": 134.259, "close": 134.33, "high": 134.34, "low": 134.159, "volume": 504737}, {"date": "2026-03-02", "open": 134.344, "close": 134.498, "high": 134.508, "low": 134.344, "volume": 176491}, {"date": "2026-03-03", "open": 134.5, "close": 134.562, "high": 134.579, "low": 134.474, "volume": 549088}, {"date": "2026-03-04", "open": 134.564, "close": 134.573, "high": 134.586, "low": 134.499, "volume": 187873}, {"date": "2026-03-05", "open": 134.629, "close": 134.572, "high": 134.695, "low": 134.541, "volume": 578321}, {"date": "2026-03-06", "open": 134.6, "close": 134.616, "high": 134.633, "low": 134.569, "volume": 541188}, {"date": "2026-03-09", "open": 134.589, "close": 134.292, "high": 134.589, "low": 134.227, "volume": 389008}, {"date": "2026-03-10", "open": 134.362, "close": 134.325, "high": 134.389, "low": 134.216, "volume": 653547}, {"date": "2026-03-11", "open": 134.314, "close": 134.319, "high": 134.323, "low": 134.244, "volume": 649015}, {"date": "2026-03-12", "open": 134.319, "close": 134.378, "high": 134.39, "low": 134.275, "volume": 647699}, {"date": "2026-03-13", "open": 134.377, "close": 134.362, "high": 134.408, "low": 134.317, "volume": 651179}, {"date": "2026-03-16", "open": 134.279, "close": 134.111, "high": 134.293, "low": 134.083, "volume": 225550}, {"date": "2026-03-17", "open": 134.173, "close": 134.177, "high": 134.186, "low": 134.131, "volume": 738423}, {"date": "2026-03-18", "open": 134.216, "close": 134.365, "high": 134.371, "low": 134.16, "volume": 47916}, {"date": "2026-03-19", "open": 134.298, "close": 134.415, "high": 134.447, "low": 134.26, "volume": 385365}, {"date": "2026-03-20", "open": 134.403, "close": 134.269, "high": 134.412, "low": 134.248, "volume": 225350}, {"date": "2026-03-23", "open": 134.269, "close": 134.133, "high": 134.291, "low": 134.116, "volume": 55259}, {"date": "2026-03-24", "open": 134.228, "close": 134.24, "high": 134.256, "low": 134.125, "volume": 582925}, {"date": "2026-03-25", "open": 134.24, "close": 134.32, "high": 134.404, "low": 134.24, "volume": 506535}, {"date": "2026-03-26", "open": 134.323, "close": 134.415, "high": 134.429, "low": 134.323, "volume": 333294}, {"date": "2026-03-27", "open": 134.396, "close": 134.406, "high": 134.462, "low": 134.377, "volume": 370282}, {"date": "2026-03-30", "open": 134.496, "close": 134.565, "high": 134.567, "low": 134.42, "volume": 122561}, {"date": "2026-03-31", "open": 134.567, "close": 134.594, "high": 134.625, "low": 134.547, "volume": 538081}, {"date": "2026-04-01", "open": 134.59, "close": 134.439, "high": 134.59, "low": 134.416, "volume": 364908}, {"date": "2026-04-02", "open": 134.445, "close": 134.504, "high": 134.526, "low": 134.391, "volume": 713797}, {"date": "2026-04-03", "open": 134.499, "close": 134.51, "high": 134.57, "low": 134.486, "volume": 197616}, {"date": "2026-04-07", "open": 134.51, "close": 134.563, "high": 134.617, "low": 134.507, "volume": 616109}, {"date": "2026-04-08", "open": 134.491, "close": 134.551, "high": 134.568, "low": 134.45, "volume": 204276}, {"date": "2026-04-09", "open": 134.565, "close": 134.625, "high": 134.666, "low": 134.551, "volume": 383277}, {"date": "2026-04-10", "open": 134.628, "close": 134.641, "high": 134.669, "low": 134.572, "volume": 418751}, {"date": "2026-04-13", "open": 134.652, "close": 134.733, "high": 134.739, "low": 134.631, "volume": 255090}, {"date": "2026-04-14", "open": 134.733, "close": 134.946, "high": 135.019, "low": 134.733, "volume": 454630}, {"date": "2026-04-15", "open": 134.9, "close": 134.965, "high": 134.998, "low": 134.838, "volume": 289180}, {"date": "2026-04-16", "open": 134.465, "close": 134.982, "high": 135.077, "low": 134.465, "volume": 452432}, {"date": "2026-04-17", "open": 134.979, "close": 135.178, "high": 135.183, "low": 134.965, "volume": 566136}, {"date": "2026-04-20", "open": 135.212, "close": 135.189, "high": 135.312, "low": 135.182, "volume": 210288}, {"date": "2026-04-21", "open": 135.2, "close": 135.25, "high": 135.31, "low": 135.2, "volume": 406313}, {"date": "2026-04-22", "open": 135.368, "close": 135.421, "high": 135.471, "low": 135.327, "volume": 542130}, {"date": "2026-04-23", "open": 135.395, "close": 135.328, "high": 135.407, "low": 135.283, "volume": 477190}, {"date": "2026-04-24", "open": 135.282, "close": 135.221, "high": 135.389, "low": 135.202, "volume": 299177}, {"date": "2026-04-27", "open": 135.099, "close": 134.932, "high": 135.194, "low": 134.904, "volume": 101116}, {"date": "2026-04-28", "open": 135.04, "close": 135.124, "high": 135.156, "low": 134.993, "volume": 113821}, {"date": "2026-04-29", "open": 135.13, "close": 135.199, "high": 135.199, "low": 135.08, "volume": 476695}, {"date": "2026-04-30", "open": 135.225, "close": 135.2, "high": 135.268, "low": 135.129, "volume": 274570}, {"date": "2026-05-06", "open": 135.199, "close": 135.072, "high": 135.199, "low": 134.968, "volume": 109064}, {"date": "2026-05-07", "open": 135.103, "close": 135.088, "high": 135.142, "low": 135.043, "volume": 328205}, {"date": "2026-05-08", "open": 135.183, "close": 135.176, "high": 135.243, "low": 135.14, "volume": 117634}, {"date": "2026-05-11", "open": 135.169, "close": 135.229, "high": 135.237, "low": 135.062, "volume": 137626}, {"date": "2026-05-12", "open": 135.22, "close": 135.356, "high": 135.374, "low": 135.2, "volume": 205573}, {"date": "2026-05-13", "open": 135.334, "close": 135.41, "high": 135.44, "low": 135.316, "volume": 53058}, {"date": "2026-05-14", "open": 135.41, "close": 135.37, "high": 135.451, "low": 135.321, "volume": 77345}, {"date": "2026-05-15", "open": 135.37, "close": 135.414, "high": 135.451, "low": 135.369, "volume": 231287}, {"date": "2026-05-18", "open": 135.41, "close": 135.496, "high": 135.512, "low": 135.278, "volume": 476651}, {"date": "2026-05-19", "open": 135.543, "close": 135.646, "high": 135.68, "low": 135.5, "volume": 574926}, {"date": "2026-05-20", "open": 135.63, "close": 135.647, "high": 135.716, "low": 135.582, "volume": 160848}, {"date": "2026-05-21", "open": 135.65, "close": 135.522, "high": 135.715, "low": 135.484, "volume": 204402}, {"date": "2026-05-22", "open": 135.55, "close": 135.475, "high": 135.567, "low": 135.456, "volume": 459617}, {"date": "2026-05-25", "open": 135.52, "close": 135.529, "high": 135.534, "low": 135.453, "volume": 269782}, {"date": "2026-05-26", "open": 135.545, "close": 135.593, "high": 135.597, "low": 135.532, "volume": 234497}, {"date": "2026-05-27", "open": 135.67, "close": 135.785, "high": 135.793, "low": 135.652, "volume": 416965}, {"date": "2026-05-28", "open": 135.88, "close": 135.975, "high": 135.99, "low": 135.814, "volume": 375300}, {"date": "2026-05-29", "open": 135.923, "close": 136.008, "high": 136.051, "low": 135.882, "volume": 96185}, {"date": "2026-06-01", "open": 136.016, "close": 136.091, "high": 136.131, "low": 135.941, "volume": 93115}, {"date": "2026-06-02", "open": 136.061, "close": 136.14, "high": 136.156, "low": 136.051, "volume": 103269}, {"date": "2026-06-03", "open": 136.082, "close": 136.078, "high": 136.121, "low": 136.045, "volume": 273288}, {"date": "2026-06-04", "open": 136.078, "close": 136.133, "high": 136.155, "low": 135.951, "volume": 397208}, {"date": "2026-06-05", "open": 136.158, "close": 136.071, "high": 136.169, "low": 136.035, "volume": 192955}, {"date": "2026-06-08", "open": 136.061, "close": 135.899, "high": 136.069, "low": 135.84, "volume": 217973}, {"date": "2026-06-09", "open": 135.889, "close": 135.75, "high": 135.901, "low": 135.741, "volume": 503967}, {"date": "2026-06-10", "open": 135.808, "close": 135.653, "high": 135.848, "low": 135.645, "volume": 500305}, {"date": "2026-06-11", "open": 135.649, "close": 135.511, "high": 135.653, "low": 135.501, "volume": 290604}, {"date": "2026-06-12", "open": 135.566, "close": 135.582, "high": 135.606, "low": 135.481, "volume": 534708}, {"date": "2026-06-15", "open": 135.63, "close": 135.671, "high": 135.725, "low": 135.579, "volume": 53920}, {"date": "2026-06-16", "open": 135.699, "close": 135.838, "high": 135.841, "low": 135.672, "volume": 234636}]